fumis_wircu/__init__.py
fumis_wircu/__version__.py
fumis_wircu/const.py
fumis_wircu/exceptions.py
fumis_wircu/fumis.py
fumis_wircu/models.py
fumis_wircu-0.1.4.dist-info/METADATA
fumis_wircu-0.1.4.dist-info/WHEEL
fumis_wircu-0.1.4.dist-info/licenses/LICENSE.md
fumis_wircu-0.1.4.dist-info/RECORD
