Metadata-Version: 2.3
Name: fumis_wircu
Version: 0.1.4
Summary: Asynchronous Python client for the Fumis WiRCU API.
Project-URL: Homepage, https://github.com/aaronmunsters/fumis_wircu
Project-URL: Issues, https://github.com/aaronmunsters/fumis_wircu/issues
Author: Aäron Munsters
Author-email: Franck Nijhof <frenck@frenck.dev>
Maintainer: Aäron Munsters
License-Expression: MIT
License-File: LICENSE.md
Keywords: api,async,client,fumis,wircu
Classifier: Framework :: AsyncIO
Classifier: Intended Audience :: Developers
Classifier: License :: OSI Approved :: MIT License
Classifier: Natural Language :: English
Classifier: Operating System :: OS Independent
Classifier: Programming Language :: Python :: 3
Classifier: Programming Language :: Python :: 3.10
Classifier: Programming Language :: Python :: 3.11
Classifier: Programming Language :: Python :: 3.12
Classifier: Topic :: Home Automation
Classifier: Topic :: Software Development :: Libraries :: Python Modules
Requires-Python: >=3.10
Requires-Dist: aiohttp>=3.9.5
Requires-Dist: async-timeout>=4.0.3
Requires-Dist: yarl
